erabytse/__init__.py
erabytse/tomb.py
erabytse_tomb-0.1.0.dist-info/licenses/LICENSE
erabytse_tomb-0.1.0.dist-info/METADATA
erabytse_tomb-0.1.0.dist-info/WHEEL
erabytse_tomb-0.1.0.dist-info/entry_points.txt
erabytse_tomb-0.1.0.dist-info/top_level.txt
erabytse_tomb-0.1.0.dist-info/RECORD
