Metadata-Version: 2.4
Name: erabytse-tomb
Version: 0.1.0
Summary: A respectful cemetery for dead links — not deletion, but remembrance.
Author-email: takouzlo <f.bfalik@gmail.com>
License: MIT
Classifier: License :: OSI Approved :: MIT License
Classifier: Programming Language :: Python :: 3
Classifier: Topic :: Internet :: WWW/HTTP
Classifier: Intended Audience :: End Users/Desktop
Requires-Python: >=3.8
License-File: LICENSE
Requires-Dist: requests>=2.25.0
Dynamic: license-file
